Metadata-Version: 1.1
Name: bitcoin-deposit-worker
Version: 0.4.2
Summary: A random test lib
Home-page: https://github.com/yuanfeiz/bitcoin_deposit_worker
Author: Yuanfei Zuu
Author-email: hi@yuanfeiz.cn
License: UNKNOWN
Download-URL: https://github.com/yuanfeiz/bitcoin_deposit_worker/archive/master.zip
Keywords: testing,logging,example
Platform: UNKNOWN
